compatibility/__init__.py
compatibility/__main__.py
compatibility/_version.py
compatibility/messages.py
compatibility/py.typed
compatibility-1.0.1.dist-info/LICENSE
compatibility-1.0.1.dist-info/METADATA
compatibility-1.0.1.dist-info/WHEEL
compatibility-1.0.1.dist-info/top_level.txt
compatibility-1.0.1.dist-info/RECORD
